<?xml version="1.0" encoding="utf-8"?>

<lang>
	<main_menubar>
		<file name="File">
			<open_pref_path>Tercih klasörünü aç</open_pref_path>
			<install_firmware>Yazılım yükle</install_firmware>
			<install_pkg>.pkg yükle</install_pkg>
			<install_zip>.zip, .vpk yükle</install_zip>
			<install_license>Lisans yükle</install_license>
		</file>
		<emulation name="Emulation">
			<last_apps_used>Son kullanma</last_apps_used>
		</emulation>
		<configuration name="Configuration">
			<settings>Ayarlar</settings>
			<user_management>Kullanıcı yönetimi</user_management>
		</configuration>
		<controls name="Controls">
			<keyboard_controls>Klavye kontrolleri</keyboard_controls>
		</controls>
		<help name="Help">
			<about>Hakkında</about>
			<welcome>Hoşgeldin</welcome>
		</help>
	</main_menubar>
	
	<app_context>
		<update_history>Geçmişi güncelle</update_history>
		<information>Bilgi</information>
		<app_delete>Uygulama hakkında bütün veriler, Kayıt dosyaları silinsinmi?</app_delete>
		<save_delete>Tüm kayıt dosyaları silinsinmi?</save_delete>
		<name>İsim</name>
		<trophy_earning eligible="Eligible" ineligible="Ineligible">Kupa kazanma</trophy_earning>
		<parental_Controls level="Level">Ebeveyn kontrolü</parental_Controls>
		<updated>güncellendi</updated>
		<size>Boyut</size>
		<version>Versiyon</version>
		<last_time_used>Son kullanma</last_time_used>
		<never>Asla</never>
		<time_used>Süre kullanıldı</time_used>
	</app_context>

	<common>
		<cancel>Geri</cancel>
		<delete>Sil</delete>
		<file_corrupted>Dosya bozuk.</file_corrupted>
		<no>Hayır</no>
		<select_all>Tümünü seç</select_all>
		<select>Seç</select>
		<please_wait>Lütfen bekleyin...</please_wait>
		<yes>Evet</yes>
		<wday>
			<day>Pazar</day>
			<day>Pazartesi</day>
			<day>Salı</day>
			<day>Çarşamba</day>
			<day>Perşembe</day>
			<day>Cuma</day>
			<day>Cumartesi</day>
		</wday>
		<ymonth>
			<month>Ocak</month>
			<month>Şubat</month>
			<month>Mart</month>
			<month>Nisan</month>
			<month>Mayıs</month>
			<month>Haziran</month>
			<month>Temmuz</month>
			<month>Ağustos</month>
			<month>Eylül</month>
			<month>Ekim</month>
			<month>Kasım</month>
			<month>Aralık</month>
		</ymonth>
		<small_ymonth>
			<month>ocak</month>
			<month>şubat</month>
			<month>mart</month>
			<month>nisan</month>
			<month>mayıs</month>
			<month>haziran</month>
			<month>temmuz</month>
			<month>ağustos</month>
			<month>eylül</month>
			<month>ekim</month>
			<month>kasım</month>
			<month>aralık</month>
		</small_ymonth>
		<hidden_trophy>Gizli kupa</hidden_trophy>
		<one_hour_ago>1 Saat Önce</one_hour_ago>
		<one_minute_ago>1 Dakika Önce</one_minute_ago>
		<bronze>Bronz</bronze>
		<gold>Altın</gold>
		<platinum>Platinyum</platinum>
		<silver>Gümüş</silver>
		<hours_ago>{} Saat Önce</hours_ago>
		<minutes_ago>{} Dakika Önce</minutes_ago>
	</common>

	<dialog>
		<trophy>
			<preparing_start_app>Uygulama başlatılıyor...</preparing_start_app>
		</trophy>
		<save_data>
			<delete>
				<cancel_deleting>Silme iptal etmek istermisiniz?</cancel_deleting>
				<deletion_complete>Silme işlemi tamamlandı.</deletion_complete>
				<delete_saved_data>Kayıt dosyalarını silmek istediğinden emin misin?</delete_saved_data>
			</delete>
			<info>
				<details>Detaylar</details>
				<updated>güncellendi</updated>
			</info>
			<load name="Load">
				<cancel_loading>Yükleme işlemini iptal etmek istediğinden emin misin?</cancel_loading>
				<no_saved_data>Kayıt dosyası bulunamadı.</no_saved_data>
				<load_complete>Yükleme Tamamlandı.</load_complete>
				<loading>Yükleniyor...</loading>
				<load_saved_data>Bu kayıt dosyasını yüklemek istediğinden emin misin?</load_saved_data>
			</load>
			<save name="Save">
				<cancel_saving>Kaydetme işlemini iptal etmek istediğinden emin misin?</cancel_saving>
				<could_not_save>Dosya kaydedilemedi. Hafıza kartında yeterli alan yok.</could_not_save>
				<not_free_space>Hafıza kartında yeterli alan yok.</not_free_space>
				<new_saved_data>Yeni Kayıt Dosyası</new_saved_data>
				<saving_complete>Kaydetme işlemi tamamlandı.</saving_complete>
				<save_the_data>Kaydetmek istediğinden emin misin?</save_the_data>
				<saving>Kaydediliyor...</saving>
				<warning_saving>Kaydediliyor...
Sistemi veya programı kapatmayın.</warning_saving>
				<overwrite_saved_data>Eski kayıtının üzerine emin misin?</overwrite_saved_data>
			</save>
		</save_data>
	</dialog>

	<game_data>
		<app_close>Program kapatılıyor.</app_close>
	</game_data>

	<indicator>
		<app_added_home>Program ana ekrana eklendi.</app_added_home>
		<delete_all>Tümünü Sil</delete_all>
		<notif_deleted>Bildirim ler silindi.</notif_deleted>
		<install_failed>Yüklenemedi.</install_failed>
		<install_complete>Yükleme Tamamlandı.</install_complete>
		<installing>Yükleniyor...</installing>
		<no_notif>Hiç bildirim yok.</no_notif>
		<trophy_earned>Bir kupa kazandın!</trophy_earned>
	</indicator>

	<live_area>
		<start>Başlat</start>
		<continue>Devam et</continue>
	</live_area>

	<settings name="Settings">
		<theme_background name="Theme & Background" default="Default">
			<theme name="Theme">
				<information name="Information">
					<name>Ad</name>
					<provider>Sağlayıcı</provider>
					<updated>güncellendi</updated>
					<size>Boyut</size>
					<version>Versiyon</version>
				</information>
				<delete>Bu tema silinecek. Emin misin.</delete>
			</theme>
			<start_screen name="Start Screen">
				<image>Resim</image>
			</start_screen>
			<home_screen_backgrounds>Ana ekran arka planları</home_screen_backgrounds>
		</theme_background>
		<date_time name="Date & Time">
			<date_format name ="Date Format">
				<yyyy_mm_dd>YYYY/AA/GG</yyyy_mm_dd>
				<dd_mm_yyyy>GG/AA/YYYY</dd_mm_yyyy>
				<mm_dd_yyyy>AA/GG/YYYY</mm_dd_yyyy>
			</date_format>
			<time_format name="Time Format">
				<clock_12_hour>12 saatlik sistem</clock_12_hour>
				<clock_24_hour>24 saatlik sistem</clock_24_hour>
			</time_format>
		</date_time>
		<language name="Language">
			<system_language>System Language</system_language>
			<input_language name="Giriş dili">
				<keyboards name="Klavyeler">
					<ime_langagues>
						<lang id="1">Danimarka</lang>
						<lang id="2">Almanya</lang>
						<lang id="262144">İngilizce (Birleşik krallık)</lang>
						<lang id="4">İngilizce (Amerika)</lang>
						<lang id="8">İspanyolca</lang>
						<lang id="16">Fransızca</lang>
						<lang id="32">İtalyanca</lang>
						<lang id="64">Flemenkçe</lang>
						<lang id="128">Norveççe</lang>
						<lang id="256">Lehçe</lang>
						<lang id="131072">Portekizce (Brezilya)</lang>
						<lang id="512">Portekizce (Portekiz)</lang>
						<lang id="1024">Rusça</lang>
						<lang id="2048">Fince</lang>
						<lang id="4096">İscveççe</lang>
						<lang id="524288">Türkçe</lang>
					</ime_langagues>
				</keyboards>
			</input_language>
		</language>
	</settings>

	<trophy_collection>
		<details>Detaylar</details>
		<earned>kazanılanlar</earned>
		<name>Ad</name>
		<no_trophies>Burada kupa yok.
Programın desteklediği oyunlardan kupa kazanabilirsin.</no_trophies>
		<not_earned>kazanılmayanlar</not_earned>
		<original>Orjinal</original>
		<sort>Sırala</sort>
		<trophies>Kupalar</trophies>
		<grade>Seviye</grade>
		<progress>İlerleme</progress>
		<updated>Güncellendi</updated>
	</trophy_collection>

	<user_management>
		<create_user>Kullanıcı oluştur</create_user>
		<edit_user>Kullanıcıyı düzenle</edit_user>
		<delete_user>Kullanıcıyı sil</delete_user>
		<change_avatar>Kullanıcı değiştir</change_avatar>
		<name>Ad</name>
		<user>Kullanıcı</user>
		<confirm>Onayla</confirm>
	</user_management>
</lang>

